beltonapi/__init__.py
beltonapi-0.1.1.dist-info/METADATA
beltonapi-0.1.1.dist-info/WHEEL
beltonapi-0.1.1.dist-info/entry_points.txt
beltonapi-0.1.1.dist-info/RECORD
