Metadata-Version: 2.1
Name: beltonapi
Version: 0.1.1
Summary: CLI for open source framework.
Home-page: https://cli.belton.team
Author: Belton Team
Author-email: support@belton.team
Requires-Python: >=3.13,<4.0
Classifier: Environment :: Console
Classifier: Environment :: Web Environment
Classifier: Programming Language :: Python
Classifier: Programming Language :: Python :: 3
Classifier: Programming Language :: Python :: 3.13
Classifier: Topic :: Internet
Classifier: Topic :: Internet :: WWW/HTTP
Classifier: Topic :: Internet :: WWW/HTTP :: HTTP Servers
Classifier: Topic :: Software Development
Classifier: Topic :: Software Development :: Build Tools
Classifier: Topic :: Software Development :: Libraries
Classifier: Topic :: Software Development :: Libraries :: Application Frameworks
Classifier: Topic :: Software Development :: Libraries :: Python Modules
Classifier: Typing :: Typed
Project-URL: Documentation, https://cli.belton.team/docs
Project-URL: Repository, https://github.com/Belton-Team/belton-pip
